json2tfvars.py
json2tfvars-0.0.1.dist-info/LICENSE
json2tfvars-0.0.1.dist-info/METADATA
json2tfvars-0.0.1.dist-info/WHEEL
json2tfvars-0.0.1.dist-info/entry_points.txt
json2tfvars-0.0.1.dist-info/top_level.txt
json2tfvars-0.0.1.dist-info/RECORD
