Metadata-Version: 2.1
Name: json2tfvars
Version: 0.0.1
Summary: simple tfvars (HCL) converter
Home-page: https://github.com/sk4zuzu/json2tfvars
Author: Michal Opala
Author-email: sk4zuzu@gmail.com
License: UNKNOWN
Platform: UNKNOWN
Classifier: License :: OSI Approved :: MIT License
Classifier: Programming Language :: Python
Classifier: Programming Language :: Python :: 2
Classifier: Programming Language :: Python :: 3
Classifier: Development Status :: 3 - Alpha
Classifier: Operating System :: OS Independent
Requires-Dist: pyhcl
